{
    "p_isSmokeDetected": "FireType",
    "p_isFireDetected": "FireType",
    "p_isCowlingAreaDiscolorationDetected": "",
    "p_isElectricFire": "FireType",
    "p_isEngineFire": "FireType",
    "p_isWingFire": "FireType",
    "p_isFireColorRed": "FireColor",

    "p_isMental": "HealthEmergencyType",
    "p_isPhysical": "HealthEmergencyType",
    "p_isSingleLadingGear": "LandingGearEmergency",
    "p_isOn": "InteractableElements",
    "p_isOff": "InteractableElements",
    "p_isPositionReached": "Position",
    "p_isCabinVentsClosed": "",
    "p_isPerformed": "ExtPerformableActions",
    "p_isPulledOut": "Valve",
    "p_isPulledIn": "Valve",

    "p_isSide": "LandingGearEmergency", 
    "p_isNose": "LandingGearEmergency"

  }
  